graphfusion/__init__.py
graphfusion/knowledge_graph.py
graphfusion/memory_manager.py
graphfusion/nmn_core.py
graphfusion/recommendation_engine.py
graphfusion-0.1.4.dist-info/METADATA
graphfusion-0.1.4.dist-info/WHEEL
graphfusion-0.1.4.dist-info/top_level.txt
graphfusion-0.1.4.dist-info/RECORD
