Metadata-Version: 2.1
Name: graphfusion
Version: 0.1.4
Summary: GraphFusion Neural Memory Network SDK for adaptive knowledge management.
Home-page: https://github.com/yourusername/graphfusion
Author: Kiplangat Korir
Author-email: Korir@GraphFusion.onmicrosoft.com
Classifier: Programming Language :: Python :: 3
Classifier: Operating System :: OS Independent
Requires-Python: >=3.6
Requires-Dist: torch
Requires-Dist: transformers
Requires-Dist: networkx
Requires-Dist: scikit-learn
Requires-Dist: numpy
Requires-Dist: pandas
Requires-Dist: matplotlib
Requires-Dist: tqdm
Requires-Dist: flask
Requires-Dist: pytest
